{
    "sets":  {
                 "archers":  "archer",
                 "hunters":  "hunter",
                 "ocelot_armor":  "ocelot",
                 "shadow_walker_armor":  "shadowwalker",
                 "spelunker_armor":  "spelunker",
                 "cave_crawler":  "cave",
                 "wolf_armor":  "wolf",
                 "black_wolf_armor":  "blackwolf",
                 "fox_armor":  "fox",
                 "arctic_fox_armor":  "arctic",
                 "climbing_gear":  "climbing",
                 "rugged_climbing_gear":  "rugged",
                 "squid_armor":  "squid",
                 "glow_squid_armor":  "glowsquid",
                 "goat_gear":  "goat",
                 "battle_robe":  "battle",
                 "splendid_robe":  "splendid",
                 "evocation_robe":  "evocation",
                 "ember_robe":  "ember",
                 "verdant_robe":  "verdant",
                 "thief_armor":  "thief",
                 "spider_armor":  "spider",
                 "soul_robe":  "soulrobe",
                 "souldancer_robe":  "souldancer",
                 "sprout_armor":  "sprout",
                 "living_vines_armor":  "livingvines",
                 "piglin_armor":  "piglin",
                 "entertainer_garb":  "entertainer",
                 "troubadour_armor":  "troubadour",
                 "teleportation_robe":  "teleportation",
                 "unstable_robe":  "unstable",
                 "phantom_armor":  "phantom",
                 "frost_bite_armor":  "frostbite",
                 "grim_armor":  "grim",
                 "wither_armor":  "wither",
                 "turtle_armor":  "turtle",
                 "nimble_turtle_armor":  "nimbleturtle",
                 "scale_mail":  "scale",
                 "highland_armor":  "highland",
                 "beehive_armor":  "beehive",
                 "beenest_armor":  "beenest",
                 "ghostly_armor":  "ghostly",
                 "ghost_kindler":  "ghostkindler",
                 "golden_piglin_armor":  "goldenpiglin",
                 "sweet_tooth":  "sweettooth",
                 "vanguard_armor":  "vanguard",
                 "reinforced_mail":  "reinforced",
                 "stalwart_armor":  "stalwart",
                 "guards_armor":  "guards",
                 "curious_armor":  "curious",
                 "snow_armor":  "snow",
                 "frost_armor":  "frost",
                 "mercenary_armor":  "mercenary",
                 "renegade_armor":  "renegade",
                 "hungry_horror":  "hungryhorror",
                 "emerald_gear":  "emeraldgear",
                 "opulent_armor":  "opulentarmor",
                 "dark_armor":  "dark",
                 "titans_shroud":  "titans",
                 "royal_guard_armor":  "royalguard",
                 "plate_armor":  "plate",
                 "full_metal_armor":  "fullmetal",
                 "white_mystery_armor":  "whitemystery",
                 "blue_mystery_armor":  "bluemystery",
                 "green_mystery_armor":  "greenmystery",
                 "purple_mystery_armor":  "purplemystery",
                 "red_mystery_armor":  "redmystery",
                 "champions_armor":  "champions",
                 "heros_armor":  "heros",
                 "gilded_glory":  "gildedglory",
                 "shulker_armor":  "shulker",
                 "sturdy_shulker_armor":  "sturdyshulker",
                 "cauldron_armor":  "cauldron",
                 "gourdian_armor":  "gourdian"
             }
}